AUTHORS.rst
CHANGELOG.rst
LICENSE
MANIFEST.in
README.rst
setup.py
asc/__init__.py
asc/parser.py
asc/contrib/__init__.py
asc/contrib/music/__init__.py
asc/contrib/music/importer.py
python_asc.egg-info/PKG-INFO
python_asc.egg-info/SOURCES.txt
python_asc.egg-info/dependency_links.txt
python_asc.egg-info/not-zip-safe
python_asc.egg-info/top_level.txt