Metadata-Version: 1.0
Name: python-asc
Version: 0.0.1
Summary: Simple Python library parsing ASC EPG feeds.
Home-page: https://github.com/praekelt/python-asc
Author: Praekelt Foundation
Author-email: dev@praekelt.com
License: BSD
Platform: UNKNOWN
Classifier: Programming Language :: Python
Classifier: License :: OSI Approved :: BSD License
Classifier: Development Status :: 4 - Beta
Classifier: Operating System :: OS Independent
Classifier: Intended Audience :: Developers
Classifier: Topic :: Internet :: WWW/HTTP :: Dynamic Content
